onyx.core-1.0.4-py3.9-nspkg.pth
onyx/core/__init__.py
onyx/core/database/__init__.py
onyx/core/database/objdb.py
onyx/core/database/objdb_api.py
onyx/core/database/tsdb.py
onyx/core/database/tsdb_api.py
onyx/core/database/ufo_base.py
onyx/core/database/ufo_fields.py
onyx/core/database/test/__init__.py
onyx/core/database/test/test_objdb.py
onyx/core/database/test/test_objdb_api.py
onyx/core/database/test/test_ufo_base.py
onyx/core/database/test/ufo_testcls.py
onyx/core/datatypes/__init__.py
onyx/core/datatypes/curve.py
onyx/core/datatypes/date.py
onyx/core/datatypes/gcurve.py
onyx/core/datatypes/hlocv.py
onyx/core/datatypes/holiday_cal.py
onyx/core/datatypes/rdate.py
onyx/core/datatypes/structure.py
onyx/core/datatypes/table.py
onyx/core/datatypes/test/__init__.py
onyx/core/datatypes/test/test_curve.py
onyx/core/datatypes/test/test_date.py
onyx/core/datatypes/test/test_gcurve.py
onyx/core/datatypes/test/test_hlocv.py
onyx/core/datatypes/test/test_rdate.py
onyx/core/datatypes/test/test_structure.py
onyx/core/datatypes/test/test_table.py
onyx/core/depgraph/__init__.py
onyx/core/depgraph/graph.py
onyx/core/depgraph/graph_api.py
onyx/core/depgraph/graph_node_descriptors.py
onyx/core/depgraph/graph_scopes.py
onyx/core/depgraph/ufo_archivable.py
onyx/core/depgraph/ufo_functions.py
onyx/core/depgraph/docs/diamond.png
onyx/core/depgraph/docs/diamond.xml
onyx/core/depgraph/docs/edge dependency.png
onyx/core/depgraph/docs/graphs.docx
onyx/core/depgraph/docs/graphs.xml
onyx/core/depgraph/test/__init__.py
onyx/core/depgraph/test/test_DCF_model.py
onyx/core/depgraph/test/test_closure.py
onyx/core/depgraph/test/test_diamond.py
onyx/core/depgraph/test/test_dynamic.py
onyx/core/depgraph/test/test_fibonacci.py
onyx/core/depgraph/test/test_graph_api.py
onyx/core/depgraph/test/test_graph_scopes.py
onyx/core/depgraph/test/test_node_types.py
onyx/core/depgraph/test/test_simple.py
onyx/core/libs/__init__.py
onyx/core/libs/curve_fns.py
onyx/core/libs/date_fns.py
onyx.core-1.0.4.dist-info/LICENSE.txt
onyx.core-1.0.4.dist-info/METADATA
onyx.core-1.0.4.dist-info/WHEEL
onyx.core-1.0.4.dist-info/entry_points.txt
onyx.core-1.0.4.dist-info/namespace_packages.txt
onyx.core-1.0.4.dist-info/top_level.txt
onyx.core-1.0.4.dist-info/RECORD
