Metadata-Version: 2.1
Name: onyx.core
Version: 1.0.4
Summary: Core functions and datatypes for the onyx framework.
Home-page: https://github.com/sbraccia/onyx.core
Author: carlo sbraccia
Author-email: carlo.sbraccia@gmail.com
License: UNKNOWN
Platform: UNKNOWN
Classifier: Development Status :: 6 - Mature
Classifier: Environment :: Console
Classifier: Intended Audience :: Developers
Classifier: Intended Audience :: Financial and Insurance Industry
Classifier: License :: OSI Approved :: Apache Software License
Classifier: Natural Language :: English
Classifier: Operating System :: OS Independent
Classifier: Programming Language :: Python :: 3.5
Classifier: Topic :: Software Development :: Libraries :: Python Modules
Classifier: Topic :: Software Development :: Libraries :: Application Frameworks
License-File: LICENSE.txt
Requires-Dist: dateutils
Requires-Dist: numpy
Requires-Dist: psycopg2
Requires-Dist: argh
